gituhubu/__init__.py
gituhubu/api.py
gituhubu/config.py
gituhubu/local_storage.py
gituhubu/utils.py
gituhubu-0.2.0.data/scripts/gituhubu
gituhubu-0.2.0.dist-info/LICENSE.txt
gituhubu-0.2.0.dist-info/METADATA
gituhubu-0.2.0.dist-info/WHEEL
gituhubu-0.2.0.dist-info/top_level.txt
gituhubu-0.2.0.dist-info/RECORD
