Metadata-Version: 2.1
Name: gituhubu
Version: 0.2.0
Summary: CLI tool for searching github organization repositories using fzf
Home-page: https://github.com/jzyinq/gituhubu
Author: Jaroslaw Zywert
Author-email: zywert@gmail.com
License: UNKNOWN
Platform: UNKNOWN
Classifier: Programming Language :: Python :: 3
Classifier: License :: OSI Approved :: MIT License
Classifier: Operating System :: OS Independent
Requires-Python: >=3.6.0
Requires-Dist: appdirs (<2,>=1.4.3)
Requires-Dist: getch (<2,>=1.0)
Requires-Dist: iterfzf (>=0.4.0.17.3)
Requires-Dist: requests (<3,>=2.22.0)
